Workbook

Sheet Backlog
A1: ID | B1: Tool | C1: Cluster | D1: Query (Guide Title) | E1: Slug | F1: Category | G1: Priority | H1: Status | I1: Notes
A2: 1 | B2: DifficultTalkCoach | C2: Upward | D2: How to tell your boss they're wrong | E2: how-to-tell-your-boss-theyre-wrong | F2: workplace | G2: High | H2: Shipped | I2: Anchor guide / exemplar
A3: 2 | B3: DifficultTalkCoach | C3: Upward | D3: How to say no to your boss | E3: how-to-say-no-to-your-boss | F3: workplace | G3: High | H3: Shipped
A4: 3 | B4: DifficultTalkCoach | C4: Upward | D4: How to push back on your boss professionally | E4: how-to-push-back-on-your-boss-professionally | F4: workplace | G4: High | H4: Shipped
A5: 4 | B5: DifficultTalkCoach | C5: Upward | D5: How to tell your boss a deadline is unrealistic | E5: how-to-tell-your-boss-a-deadline-is-unrealistic | F5: workplace | G5: High | H5: Shipped
A6: 5 | B6: DifficultTalkCoach | C6: Upward | D6: How to tell your manager their feedback is unfair | E6: how-to-tell-your-manager-their-feedback-is-unfair | F6: workplace | G6: High | H6: Shipped
A7: 6 | B7: DifficultTalkCoach | C7: Upward | D7: How to ask your boss for a raise | E7: how-to-ask-your-boss-for-a-raise | F7: workplace | G7: High | H7: Candidate | I7: Highest-volume query in this family
A8: 7 | B8: DifficultTalkCoach | C8: Upward | D8: How to tell your boss you're burned out | E8: how-to-tell-your-boss-youre-burned-out | F8: workplace | G8: High | H8: Candidate | I8: Rising trend, emotionally loaded
A9: 8 | B9: DifficultTalkCoach | C9: Upward | D9: How to tell your boss you made a mistake | E9: how-to-tell-your-boss-you-made-a-mistake | F9: workplace | G9: High | H9: Candidate | I9: Classic stakes moment
A10: 9 | B10: DifficultTalkCoach | C10: Upward | D10: How to tell your boss you're quitting | E10: how-to-tell-your-boss-youre-quitting | F10: workplace | G10: High | H10: Candidate | I10: Commercial intent, evergreen
A11: 15 | B11: DifficultTalkCoach | C11: Lateral | D11: How to tell a coworker they're being rude | E11: how-to-tell-a-coworker-theyre-being-rude | F11: workplace | G11: High | H11: Candidate | I11: Classic query
A12: 16 | B12: DifficultTalkCoach | C12: Lateral | D12: How to handle a coworker who takes credit for your work | E12: how-to-handle-a-coworker-who-takes-credit-for-your-work | F12: workplace | G12: High | H12: Candidate | I12: Evergreen, high volume
A13: 17 | B13: DifficultTalkCoach | C13: Lateral | D13: How to respond to a passive aggressive email | E13: how-to-respond-to-a-passive-aggressive-email | F13: workplace | G13: High | H13: Candidate | I13: Directly quoted in audience report
A14: 18 | B14: DifficultTalkCoach | C14: Lateral | D14: How to tell a coworker they smell | E14: how-to-tell-a-coworker-they-smell | F14: workplace | G14: High | H14: Candidate | I14: High volume, real pain
A15: 19 | B15: DifficultTalkCoach | C15: Lateral | D15: How to deal with a coworker who talks too much in meetings | E15: how-to-deal-with-a-coworker-who-talks-too-much-in-meetings | F15: workplace | G15: High | H15: Candidate | I15: Specific, recognizable
A16: 20 | B16: DifficultTalkCoach | C16: Lateral | D16: How to confront a coworker about their behavior | E16: how-to-confront-a-coworker-about-their-behavior | F16: workplace | G16: High | H16: Candidate | I16: Broad umbrella query
A17: 29 | B17: DifficultTalkCoach | C17: Downward | D17: How to give constructive criticism to an employee | E17: how-to-give-constructive-criticism-to-an-employee | F17: workplace | G17: High | H17: Candidate | I17: Evergreen management query
A18: 30 | B18: DifficultTalkCoach | C18: Downward | D18: How to tell an employee their performance is slipping | E18: how-to-tell-an-employee-their-performance-is-slipping | F18: workplace | G18: High | H18: Candidate | I18: Classic moment
... A97: 96 | B97: DifficultTalkCoach | C97: Apology | D97: How to apologize for hurting someone's feelings when you didn't mean to | E97: how-to-apologize-for-hurting-someones-feelings-when-you-didnt-mean-to | F97: conversations | G97: Medium | H97: Candidate | I97: Nuanced
A98: 1 | B98: DoctorVisitPrep | C98: Before | D98: How to prepare for a doctor's appointment | E98: how-to-prepare-for-a-doctors-appointment | F98: health | G98: High | H98: Shipped
A99: 2 | B99: DoctorVisitPrep | C99: Before | D99: What questions to ask your doctor | E99: questions-to-ask-your-doctor | F99: health | G99: High | H99: Shipped
A100: 3 | B100: DoctorVisitPrep | C100: Before | D100: How to describe your symptoms to a doctor | E100: how-to-describe-your-symptoms-to-a-doctor | F100: health | G100: High | H100: Shipped
A101: 7 | B101: DoctorVisitPrep | C101: Before | D101: How to get your concerns taken seriously at the doctor | E101: how-to-get-your-concerns-taken-seriously-at-the-doctor | F101: health | G101: High | H101: Shipped | I101: VOICE: sensitive
A102: 8 | B102: DoctorVisitTranslator | C102: Understand | D102: How to understand what your doctor actually said | E102: how-to-understand-what-your-doctor-actually-said | F102: health | G102: High | H102: Shipped
A103: 13 | B103: DoctorVisitTranslator | C103: Tests | D103: How to read your blood test results | E103: how-to-read-your-blood-test-results | F103: health | G103: High | H103: Candidate
A104: 20 | B104: DoctorVisitPrep | C104: Medication | D104: What to ask before taking a new medication | E104: what-to-ask-before-taking-a-new-medication | F104: health | G104: High | H104: Candidate
A105: 26 | B105: DoctorVisitPrep | C105: Advocacy | D105: How to push back when a doctor isn't listening | E105: how-to-push-back-when-a-doctor-isnt-listening | F105: health | G105: High | H105: Candidate | I105: OVERLAP: DifficultTalkCoach; VOICE: sensitive
A106: 27 | B106: DoctorVisitPrep | C106: Advocacy | D106: How to get a doctor to take your pain seriously | E106: how-to-get-a-doctor-to-take-your-pain-seriously | F106: health | G106: High | H106: Candidate | I106: VOICE: sensitive
A107: 28 | B107: DoctorVisitPrep | C107: Advocacy | D107: How to get a second opinion | E107: how-to-get-a-second-opinion | F107: health | G107: High | H107: Candidate
A108: 30 | B108: DoctorVisitPrep | C108: Advocacy | D108: How to advocate for yourself at the doctor | E108: how-to-advocate-for-yourself-at-the-doctor | F108: health | G108: High | H108: Candidate
A109: 37 | B109: DoctorVisitTranslator | C109: Diagnosis | D109: How to understand a cancer diagnosis | E109: how-to-understand-a-cancer-diagnosis | F109: health | G109: High | H109: Candidate | I109: VOICE: full empathy register. No dry humor.
A110: 6 | B110: DoctorVisitPrep | C110: Before | D110: What to bring to a doctor's appointment | E110: what-to-bring-to-a-doctors-appointment | F110: health | G110: Low | H110: Candidate
A111: 12 | B111: DoctorVisitPrep | C111: Understand | D111: How to take notes during a doctor's appointment | E111: how-to-take-notes-during-a-doctors-appointment | F111: health | G111: Low | H111: Candidate
A112: 25 | B112: DoctorVisitTranslator | C112: Medication | D112: How to read a prescription label | E112: how-to-read-a-prescription-label | F112: health | G112: Low | H112: Candidate
A113: 4 | B113: DoctorVisitPrep | C113: Before | D113: How to make the most of a 15-minute doctor visit | E113: how-to-make-the-most-of-a-15-minute-doctor-visit | F113: health | G113: Medium | H113: Candidate
A114: 5 | B114: DoctorVisitPrep | C114: Before | D114: How to prepare for a first appointment with a new doctor | E114: how-to-prepare-for-a-first-appointment-with-a-new-doctor | F114: health | G114: Medium | H114: Candidate
A115: 9 | B115: DoctorVisitPrep | C115: Understand | D115: How to ask a doctor to explain something | E115: how-to-ask-a-doctor-to-explain-something | F115: health | G115: Medium | H115: Candidate
A116: 10 | B116: DoctorVisitTranslator | C116: Understand | D116: How to understand medical jargon | E116: how-to-understand-medical-jargon | F116: health | G116: Medium | H116: Candidate
A117: 11 | B117: DoctorVisitTranslator | C117: Understand | D117: How to translate a doctor's note into plain language | E117: how-to-translate-a-doctors-note-into-plain-language | F117: health | G117: Medium | H117: Candidate
A118: 14 | B118: DoctorVisitTranslator | C118: Tests | D118: What does abnormal mean on a blood test | E118: what-does-abnormal-mean-on-a-blood-test | F118: health | G118: Medium | H118: Candidate
A119: 15 | B119: DoctorVisitTranslator | C119: Tests | D119: How to understand an MRI report | E119: how-to-understand-an-mri-report | F119: health | G119: Medium | H119: Candidate
A120: 16 | B120: DoctorVisitTranslator | C120: Tests | D120: How to interpret lab results | E120: how-to-interpret-lab-results | F120: health | G120: Medium | H120: Candidate
A121: 17 | B121: DoctorVisitTranslator | C121: Tests | D121: How to understand a biopsy report | E121: how-to-understand-a-biopsy-report | F121: health | G121: Medium | H121: Candidate | I121: VOICE: sensitive
A122: 18 | B122: DoctorVisitTranslator | C122: Tests | D122: How to read an imaging report | E122: how-to-read-an-imaging-report | F122: health | G122: Medium | H122: Candidate
A123: 19 | B123: DoctorVisitTranslator | C123: Tests | D123: What do borderline test results mean | E123: what-do-borderline-test-results-mean | F123: health | G123: Medium | H123: Candidate
A124: 21 | B124: DoctorVisitTranslator | C124: Medication | D124: How to understand medication side effects | E124: how-to-understand-medication-side-effects | F124: health | G124: Medium | H124: Candidate
A125: 22 | B125: DoctorVisitTranslator | C125: Medication | D125: How to tell if a medication is working | E125: how-to-tell-if-a-medication-is-working | F125: health | G125: Medium | H125: Candidate
A126: 23 | B126: DoctorVisitPrep | C126: Medication | D126: How to talk to your doctor about side effects | E126: how-to-talk-to-your-doctor-about-side-effects | F126: health | G126: Medium | H126: Candidate
A127: 24 | B127: DoctorVisitPrep | C127: Medication | D127: How to ask for a different medication | E127: how-to-ask-for-a-different-medication | F127: health | G127: Medium | H127: Candidate
A128: 29 | B128: DoctorVisitPrep | C128: Advocacy | D128: How to ask for more tests | E128: how-to-ask-for-more-tests | F128: health | G128: Medium | H128: Candidate
A129: 31 | B129: DoctorVisitPrep | C129: Advocacy | D129: How to tell if your doctor is dismissing you | E129: how-to-tell-if-your-doctor-is-dismissing-you | F129: health | G129: Medium | H129: Candidate | I129: VOICE: sensitive
A130: 32 | B130: DoctorVisitPrep | C130: Advocacy | D130: How to switch doctors without awkwardness | E130: how-to-switch-doctors-without-awkwardness | F130: health | G130: Medium | H130: Candidate | I130: OVERLAP: DifficultTalkCoach
A131: 33 | B131: DoctorVisitPrep | C131: Advocacy | D131: What to do when a doctor won't give you a diagnosis | E131: what-to-do-when-a-doctor-wont-give-you-a-diagnosis | F131: health | G131: Medium | H131: Candidate | I131: VOICE: sensitive
A132: 34 | B132: DoctorVisitPrep | C132: Specialists | D132: How to prepare for a specialist appointment | E132: how-to-prepare-for-a-specialist-appointment | F132: health | G132: Medium | H132: Candidate
A133: 35 | B133: DoctorVisitPrep | C133: Specialists | D133: What to ask a specialist on the first visit | E133: what-to-ask-a-specialist-on-the-first-visit | F133: health | G133: Medium | H133: Candidate
A134: 36 | B134: DoctorVisitTranslator | C134: Specialists | D134: How to understand what a specialist says | E134: how-to-understand-what-a-specialist-says | F134: health | G134: Medium | H134: Candidate
A135: 38 | B135: DoctorVisitPrep | C135: Diagnosis | D135: What to ask after a serious diagnosis | E135: what-to-ask-after-a-serious-diagnosis | F135: health | G135: Medium | H135: Candidate | I135: VOICE: full empathy register.
A136: 39 | B136: DoctorVisitTranslator | C136: Diagnosis | D136: How to understand a chronic illness diagnosis | E136: how-to-understand-a-chronic-illness-diagnosis | F136: health | G136: Medium | H136: Candidate | I136: VOICE: full empathy register.
A137: 40 | B137: DoctorVisitTranslator | C137: Diagnosis | D137: How to understand what stage of disease you are in | E137: how-to-understand-what-stage-of-disease-you-are-in | F137: health | G137: Medium | H137: Candidate | I137: VOICE: full empathy register. Particularly careful.
A138: 1 | B138: LeaseTrapDetector | C138: Pre-signing | D138: How to read a lease before signing it | E138: how-to-read-a-lease-before-signing-it | F138: home | G138: High | H138: Candidate | I138: Core use case
A139: 2 | B139: LeaseTrapDetector | C139: Pre-signing | D139: What to look for in an apartment lease | E139: what-to-look-for-in-an-apartment-lease | F139: home | G139: High | H139: Candidate | I139: High-volume query
A140: 3 | B140: LeaseTrapDetector | C140: Pre-signing | D140: Red flags in a rental lease | E140: red-flags-in-a-rental-lease | F140: home | G140: High | H140: Candidate
A141: 4 | B141: LeaseTrapDetector | C141: Pre-signing | D141: What to check before signing a lease | E141: what-to-check-before-signing-a-lease | F141: home | G141: High | H141: Candidate
A142: 8 | B142: LeaseTrapDetector | C142: Clauses | D142: How to understand security deposit terms in a lease | E142: how-to-understand-security-deposit-terms-in-a-lease | F142: home | G142: High | H142: Candidate | I142: Huge search volume on security deposits
A143: 15 | B143: LeaseTrapDetector | C143: Negotiation | D143: How to negotiate a lease before signing | E143: how-to-negotiate-a-lease-before-signing | F143: home | G143: High | H143: Candidate
A144: 21 | B144: LeaseTrapDetector | C144: Landlord limits | D144: Can a landlord raise your rent without notice | E144: can-a-landlord-raise-your-rent-without-notice | F144: home | G144: High | H144: Candidate | I144: LEGAL CAUTION: state laws vary
A145: 22 | B145: LeaseTrapDetector | C145: Landlord limits | D145: Can a landlord keep your security deposit | E145: can-a-landlord-keep-your-security-deposit | F145: home | G145: High | H145: Candidate | I145: LEGAL CAUTION: state laws vary
A146: 23 | B146: LeaseTrapDetector | C146: Landlord limits | D146: Can a landlord enter your apartment without permission | E146: can-a-landlord-enter-your-apartment-without-permission | F146: home | G146: High | H146: Candidate | I146: LEGAL CAUTION: state laws vary
A147: 28 | B147: LeaseTrapDetector | C147: Post-signing | D147: How to break a lease legally | E147: how-to-break-a-lease-legally | F147: home | G147: High | H147: Candidate | I147: Huge search volume
A148: 29 | B148: LeaseTrapDetector | C148: Post-signing | D148: How to get out of a lease early without paying | E148: how-to-get-out-of-a-lease-early-without-paying | F148: home | G148: High | H148: Candidate
A149: 20 | B149: LeaseTrapDetector | C149: Negotiation | D149: How to get a landlord to remove an unfair clause | E149: how-to-get-a-landlord-to-remove-an-unfair-clause | F149: home | G149: Low | H149: Candidate
A150: 37 | B150: LeaseTrapDetector | C150: Special | D150: How to review a lease as a cosigner | E150: how-to-review-a-lease-as-a-cosigner | F150: home | G150: Low | H150: Candidate
A151: 38 | B151: LeaseTrapDetector | C151: Special | D151: How to read a roommate agreement | E151: how-to-read-a-roommate-agreement | F151: home | G151: Low | H151: Candidate
A152: 5 | B152: LeaseTrapDetector | C152: Pre-signing | D152: How to spot unfair clauses in a lease | E152: how-to-spot-unfair-clauses-in-a-lease | F152: home | G152: Medium | H152: Candidate
A153: 6 | B153: LeaseTrapDetector | C153: Pre-signing | D153: How to tell if a lease is a bad deal | E153: how-to-tell-if-a-lease-is-a-bad-deal | F153: home | G153: Medium | H153: Candidate
A154: 7 | B154: LeaseTrapDetector | C154: Pre-signing | D154: How to review a lease agreement carefully | E154: how-to-review-a-lease-agreement-carefully | F154: home | G154: Medium | H154: Candidate
A155: 9 | B155: LeaseTrapDetector | C155: Clauses | D155: What is an early termination fee in a lease | E155: what-is-an-early-termination-fee-in-a-lease | F155: home | G155: Medium | H155: Candidate
A156: 10 | B156: LeaseTrapDetector | C156: Clauses | D156: How to understand automatic renewal clauses in a lease | E156: how-to-understand-automatic-renewal-clauses-in-a-lease | F156: home | G156: Medium | H156: Candidate
A157: 11 | B157: LeaseTrapDetector | C157: Clauses | D157: How to interpret the maintenance section of a lease | E157: how-to-interpret-the-maintenance-section-of-a-lease | F157: home | G157: Medium | H157: Candidate
A158: 12 | B158: LeaseTrapDetector | C158: Clauses | D158: What is joint and several liability in a lease | E158: what-is-joint-and-several-liability-in-a-lease | F158: home | G158: Medium | H158: Candidate
A159: 13 | B159: LeaseTrapDetector | C159: Clauses | D159: What are reasonable landlord fees in a lease | E159: what-are-reasonable-landlord-fees-in-a-lease | F159: home | G159: Medium | H159: Candidate
... A161: 16 | B161: LeaseTrapDetector | C161: Negotiation | D161: What lease terms are negotiable | E161: what-lease-terms-are-negotiable | F161: home | G161: Medium | H161: Candidate
A162: 17 | B162: LeaseTrapDetector | C162: Negotiation | D162: How to ask a landlord to change a lease clause | E162: how-to-ask-a-landlord-to-change-a-lease-clause | F162: home | G162: Medium | H162: Candidate | I162: Soft overlap: DifficultTalkCoach
A163: 18 | B163: LeaseTrapDetector | C163: Negotiation | D163: How to negotiate a pet deposit or pet fee | E163: how-to-negotiate-a-pet-deposit-or-pet-fee | F163: home | G163: Medium | H163: Candidate
A164: 19 | B164: LeaseTrapDetector | C164: Negotiation | D164: How to negotiate rent with a landlord | E164: how-to-negotiate-rent-with-a-landlord | F164: home | G164: Medium | H164: Candidate
A165: 24 | B165: LeaseTrapDetector | C165: Landlord limits | D165: What can a landlord legally charge fees for | E165: what-can-a-landlord-legally-charge-fees-for | F165: home | G165: Medium | H165: Candidate | I165: LEGAL CAUTION: state laws vary
A166: 25 | B166: LeaseTrapDetector | C166: Landlord limits | D166: Is a lease legally binding if the landlord misrepresented it | E166: is-a-lease-legally-binding-if-the-landlord-misrepresented-it | F166: home | G166: Medium | H166: Candidate | I166: LEGAL CAUTION: often needs a lawyer
A167: 26 | B167: LeaseTrapDetector | C167: Landlord limits | D167: Can a landlord change the terms of your lease mid-term | E167: can-a-landlord-change-the-terms-of-your-lease-mid-term | F167: home | G167: Medium | H167: Candidate | I167: LEGAL CAUTION: state laws vary
A168: 27 | B168: LeaseTrapDetector | C168: Landlord limits | D168: Can a landlord charge late fees | E168: can-a-landlord-charge-late-fees | F168: home | G168: Medium | H168: Candidate | I168: LEGAL CAUTION: state laws vary
A169: 30 | B169: LeaseTrapDetector | C169: Post-signing | D169: What to do if your lease has unfair clauses | E169: what-to-do-if-your-lease-has-unfair-clauses | F169: home | G169: Medium | H169: Candidate
A170: 31 | B170: LeaseTrapDetector | C170: Post-signing | D170: How to fight an unfair lease charge | E170: how-to-fight-an-unfair-lease-charge | F170: home | G170: Medium | H170: Candidate
A171: 32 | B171: LeaseTrapDetector | C171: Post-signing | D171: What to do when your landlord violates the lease | E171: what-to-do-when-your-landlord-violates-the-lease | F171: home | G171: Medium | H171: Candidate
A172: 33 | B172: LeaseTrapDetector | C172: Vetting | D172: How to tell if a landlord is shady before signing | E172: how-to-tell-if-a-landlord-is-shady-before-signing | F172: home | G172: Medium | H172: Candidate
A173: 34 | B173: LeaseTrapDetector | C173: Vetting | D173: Rental red flags to watch for before signing | E173: rental-red-flags-to-watch-for-before-signing | F173: home | G173: Medium | H173: Candidate
A174: 35 | B174: LeaseTrapDetector | C174: Vetting | D174: Questions to ask before signing a lease | E174: questions-to-ask-before-signing-a-lease | F174: home | G174: Medium | H174: Candidate
A175: 36 | B175: LeaseTrapDetector | C175: Special | D175: What to check before subletting a lease | E175: what-to-check-before-subletting-a-lease | F175: home | G175: Medium | H175: Candidate
A176: 1 | B176: UpsellShield | C176: Cars | D176: How to avoid getting ripped off at a car dealership | E176: how-to-avoid-getting-ripped-off-at-a-car-dealership | F176: consumer | G176: High | H176: Candidate | I176: High-volume query
A177: 2 | B177: UpsellShield | C177: Cars | D177: How to negotiate with a car salesman | E177: how-to-negotiate-with-a-car-salesman | F177: consumer | G177: High | H177: Candidate
A178: 3 | B178: UpsellShield | C178: Cars | D178: How to tell if a car dealer is lying to you | E178: how-to-tell-if-a-car-dealer-is-lying-to-you | F178: consumer | G178: High | H178: Candidate
A179: 6 | B179: UpsellShield | C179: Cars | D179: How to avoid dealer add-ons | E179: how-to-avoid-dealer-add-ons | F179: consumer | G179: High | H179: Candidate
...

Sheet Summary
A1: Tool | B1: Cluster | C1: Total Queries | D1: Shipped | E1: Candidates | F1: High Priority (remaining)
A2: DifficultTalkCoach | B2: Upward | C2: =COUNTIFS(Backlog!B:B,"DifficultTalkCoach",Backlog!C:C,"Upward") -> 14 | D2: =COUNTIFS(Backlog!B:B,"DifficultTalkCoach",Backlog!C:C,"Upward",Backlog!H:H,"Shipped") -> 5 | E2: =COUNTIFS(Backlog!B:B,"DifficultTalkCoach",Backlog!C:C,"Upward",Backlog!H:H,"Candidate") -> 9 | F2: =COUNTIFS(Backlog!B:B,"DifficultTalkCoach",Backlog!C:C,"Upward",Backlog!G:G,"High",Backlog!H:H,"Candidate") -> 4
A3: DifficultTalkCoach | B3: Lateral | C3: =COUNTIFS(Backlog!B:B,"DifficultTalkCoach",Backlog!C:C,"Lateral") -> 14 | D3: =COUNTIFS(Backlog!B:B,"DifficultTalkCoach",Backlog!C:C,"Lateral",Backlog!H:H,"Shipped") -> 0 | E3: =COUNTIFS(Backlog!B:B,"DifficultTalkCoach",Backlog!C:C,"Lateral",Backlog!H:H,"Candidate") -> 14 | F3: =COUNTIFS(Backlog!B:B,"DifficultTalkCoach",Backlog!C:C,"Lateral",Backlog!G:G,"High",Backlog!H:H,"Candidate") -> 6
A4: DifficultTalkCoach | B4: Downward | C4: =COUNTIFS(Backlog!B:B,"DifficultTalkCoach",Backlog!C:C,"Downward") -> 10 | D4: =COUNTIFS(Backlog!B:B,"DifficultTalkCoach",Backlog!C:C,"Downward",Backlog!H:H,"Shipped") -> 0 | E4: =COUNTIFS(Backlog!B:B,"DifficultTalkCoach",Backlog!C:C,"Downward",Backlog!H:H,"Candidate") -> 10 | F4: =COUNTIFS(Backlog!B:B,"DifficultTalkCoach",Backlog!C:C,"Downward",Backlog!G:G,"High",Backlog!H:H,"Candidate") -> 4
A5: DifficultTalkCoach | B5: Partner | C5: =COUNTIFS(Backlog!B:B,"DifficultTalkCoach",Backlog!C:C,"Partner") -> 13 | D5: =COUNTIFS(Backlog!B:B,"DifficultTalkCoach",Backlog!C:C,"Partner",Backlog!H:H,"Shipped") -> 0 | E5: =COUNTIFS(Backlog!B:B,"DifficultTalkCoach",Backlog!C:C,"Partner",Backlog!H:H,"Candidate") -> 13 | F5: =COUNTIFS(Backlog!B:B,"DifficultTalkCoach",Backlog!C:C,"Partner",Backlog!G:G,"High",Backlog!H:H,"Candidate") -> 5
A6: DifficultTalkCoach | B6: Family | C6: =COUNTIFS(Backlog!B:B,"DifficultTalkCoach",Backlog!C:C,"Family") -> 12 | D6: =COUNTIFS(Backlog!B:B,"DifficultTalkCoach",Backlog!C:C,"Family",Backlog!H:H,"Shipped") -> 0 | E6: =COUNTIFS(Backlog!B:B,"DifficultTalkCoach",Backlog!C:C,"Family",Backlog!H:H,"Candidate") -> 12 | F6: =COUNTIFS(Backlog!B:B,"DifficultTalkCoach",Backlog!C:C,"Family",Backlog!G:G,"High",Backlog!H:H,"Candidate") -> 4
A7: DifficultTalkCoach | B7: Friends | C7: =COUNTIFS(Backlog!B:B,"DifficultTalkCoach",Backlog!C:C,"Friends") -> 9 | D7: =COUNTIFS(Backlog!B:B,"DifficultTalkCoach",Backlog!C:C,"Friends",Backlog!H:H,"Shipped") -> 0 | E7: =COUNTIFS(Backlog!B:B,"DifficultTalkCoach",Backlog!C:C,"Friends",Backlog!H:H,"Candidate") -> 9 | F7: =COUNTIFS(Backlog!B:B,"DifficultTalkCoach",Backlog!C:C,"Friends",Backlog!G:G,"High",Backlog!H:H,"Candidate") -> 4
A8: DifficultTalkCoach | B8: Hard news | C8: =COUNTIFS(Backlog!B:B,"DifficultTalkCoach",Backlog!C:C,"Hard news") -> 6 | D8: =COUNTIFS(Backlog!B:B,"DifficultTalkCoach",Backlog!C:C,"Hard news",Backlog!H:H,"Shipped") -> 0 | E8: =COUNTIFS(Backlog!B:B,"DifficultTalkCoach",Backlog!C:C,"Hard news",Backlog!H:H,"Candidate") -> 6 | F8: =COUNTIFS(Backlog!B:B,"DifficultTalkCoach",Backlog!C:C,"Hard news",Backlog!G:G,"High",Backlog!H:H,"Candidate") -> 3
A9: DifficultTalkCoach | B9: Asking | C9: =COUNTIFS(Backlog!B:B,"DifficultTalkCoach",Backlog!C:C,"Asking") -> 7 | D9: =COUNTIFS(Backlog!B:B,"DifficultTalkCoach",Backlog!C:C,"Asking",Backlog!H:H,"Shipped") -> 0 | E9: =COUNTIFS(Backlog!B:B,"DifficultTalkCoach",Backlog!C:C,"Asking",Backlog!H:H,"Candidate") -> 7 | F9: =COUNTIFS(Backlog!B:B,"DifficultTalkCoach",Backlog!C:C,"Asking",Backlog!G:G,"High",Backlog!H:H,"Candidate") -> 4
A10: DifficultTalkCoach | B10: Saying no | C10: =COUNTIFS(Backlog!B:B,"DifficultTalkCoach",Backlog!C:C,"Saying no") -> 6 | D10: =COUNTIFS(Backlog!B:B,"DifficultTalkCoach",Backlog!C:C,"Saying no",Backlog!H:H,"Shipped") -> 0 | E10: =COUNTIFS(Backlog!B:B,"DifficultTalkCoach",Backlog!C:C,"Saying no",Backlog!H:H,"Candidate") -> 6 | F10: =COUNTIFS(Backlog!B:B,"DifficultTalkCoach",Backlog!C:C,"Saying no",Backlog!G:G,"High",Backlog!H:H,"Candidate") -> 3
A11: DifficultTalkCoach | B11: Apology | C11: =COUNTIFS(Backlog!B:B,"DifficultTalkCoach",Backlog!C:C,"Apology") -> 5 | D11: =COUNTIFS(Backlog!B:B,"DifficultTalkCoach",Backlog!C:C,"Apology",Backlog!H:H,"Shipped") -> 0 | E11: =COUNTIFS(Backlog!B:B,"DifficultTalkCoach",Backlog!C:C,"Apology",Backlog!H:H,"Candidate") -> 5 | F11: =COUNTIFS(Backlog!B:B,"DifficultTalkCoach",Backlog!C:C,"Apology",Backlog!G:G,"High",Backlog!H:H,"Candidate") -> 1
A12: UpsellShield | B12: Cars | C12: =COUNTIFS(Backlog!B:B,"UpsellShield",Backlog!C:C,"Cars") -> 9 | D12: =COUNTIFS(Backlog!B:B,"UpsellShield",Backlog!C:C,"Cars",Backlog!H:H,"Shipped") -> 0 | E12: =COUNTIFS(Backlog!B:B,"UpsellShield",Backlog!C:C,"Cars",Backlog!H:H,"Candidate") -> 9 | F12: =COUNTIFS(Backlog!B:B,"UpsellShield",Backlog!C:C,"Cars",Backlog!G:G,"High",Backlog!H:H,"Candidate") -> 5
A13: UpsellShield | B13: Subscriptions | C13: =COUNTIFS(Backlog!B:B,"UpsellShield",Backlog!C:C,"Subscriptions") -> 8 | D13: =COUNTIFS(Backlog!B:B,"UpsellShield",Backlog!C:C,"Subscriptions",Backlog!H:H,"Shipped") -> 0 | E13: =COUNTIFS(Backlog!B:B,"UpsellShield",Backlog!C:C,"Subscriptions",Backlog!H:H,"Candidate") -> 8 | F13: =COUNTIFS(Backlog!B:B,"UpsellShield",Backlog!C:C,"Subscriptions",Backlog!G:G,"High",Backlog!H:H,"Candidate") -> 5
A14: UpsellShield | B14: Services | C14: =COUNTIFS(Backlog!B:B,"UpsellShield",Backlog!C:C,"Services") -> 5 | D14: =COUNTIFS(Backlog!B:B,"UpsellShield",Backlog!C:C,"Services",Backlog!H:H,"Shipped") -> 0 | E14: =COUNTIFS(Backlog!B:B,"UpsellShield",Backlog!C:C,"Services",Backlog!H:H,"Candidate") -> 5 | F14: =COUNTIFS(Backlog!B:B,"UpsellShield",Backlog!C:C,"Services",Backlog!G:G,"High",Backlog!H:H,"Candidate") -> 1
A15: UpsellShield | B15: Pressure | C15: =COUNTIFS(Backlog!B:B,"UpsellShield",Backlog!C:C,"Pressure") -> 10 | D15: =COUNTIFS(Backlog!B:B,"UpsellShield",Backlog!C:C,"Pressure",Backlog!H:H,"Shipped") -> 0 | E15: =COUNTIFS(Backlog!B:B,"UpsellShield",Backlog!C:C,"Pressure",Backlog!H:H,"Candidate") -> 10 | F15: =COUNTIFS(Backlog!B:B,"UpsellShield",Backlog!C:C,"Pressure",Backlog!G:G,"High",Backlog!H:H,"Candidate") -> 4
A16: UpsellShield | B16: Dark patterns | C16: =COUNTIFS(Backlog!B:B,"UpsellShield",Backlog!C:C,"Dark patterns") -> 5 | D16: =COUNTIFS(Backlog!B:B,"UpsellShield",Backlog!C:C,"Dark patterns",Backlog!H:H,"Shipped") -> 0 | E16: =COUNTIFS(Backlog!B:B,"UpsellShield",Backlog!C:C,"Dark patterns",Backlog!H:H,"Candidate") -> 5 | F16: =COUNTIFS(Backlog!B:B,"UpsellShield",Backlog!C:C,"Dark patterns",Backlog!G:G,"High",Backlog!H:H,"Candidate") -> 1
A17: UpsellShield | B17: Financial | C17: =COUNTIFS(Backlog!B:B,"UpsellShield",Backlog!C:C,"Financial") -> 8 | D17: =COUNTIFS(Backlog!B:B,"UpsellShield",Backlog!C:C,"Financial",Backlog!H:H,"Shipped") -> 0 | E17: =COUNTIFS(Backlog!B:B,"UpsellShield",Backlog!C:C,"Financial",Backlog!H:H,"Candidate") -> 8 | F17: =COUNTIFS(Backlog!B:B,"UpsellShield",Backlog!C:C,"Financial",Backlog!G:G,"High",Backlog!H:H,"Candidate") -> 4
A18: UpsellShield | B18: Tactics | C18: =COUNTIFS(Backlog!B:B,"UpsellShield",Backlog!C:C,"Tactics") -> 7 | D18: =COUNTIFS(Backlog!B:B,"UpsellShield",Backlog!C:C,"Tactics",Backlog!H:H,"Shipped") -> 0 | E18: =COUNTIFS(Backlog!B:B,"UpsellShield",Backlog!C:C,"Tactics",Backlog!H:H,"Candidate") -> 7 | F18: =COUNTIFS(Backlog!B:B,"UpsellShield",Backlog!C:C,"Tactics",Backlog!G:G,"High",Backlog!H:H,"Candidate") -> 3
A19: UpsellShield | B19: Recovery | C19: =COUNTIFS(Backlog!B:B,"UpsellShield",Backlog!C:C,"Recovery") -> 5 | D19: =COUNTIFS(Backlog!B:B,"UpsellShield",Backlog!C:C,"Recovery",Backlog!H:H,"Shipped") -> 0 | E19: =COUNTIFS(Backlog!B:B,"UpsellShield",Backlog!C:C,"Recovery",Backlog!H:H,"Candidate") -> 5 | F19: =COUNTIFS(Backlog!B:B,"UpsellShield",Backlog!C:C,"Recovery",Backlog!G:G,"High",Backlog!H:H,"Candidate") -> 2
A20: LeaseTrapDetector | B20: Pre-signing | C20: =COUNTIFS(Backlog!B:B,"LeaseTrapDetector",Backlog!C:C,"Pre-signing") -> 7 | D20: =COUNTIFS(Backlog!B:B,"LeaseTrapDetector",Backlog!C:C,"Pre-signing",Backlog!H:H,"Shipped") -> 0 | E20: =COUNTIFS(Backlog!B:B,"LeaseTrapDetector",Backlog!C:C,"Pre-signing",Backlog!H:H,"Candidate") -> 7 | F20: =COUNTIFS(Backlog!B:B,"LeaseTrapDetector",Backlog!C:C,"Pre-signing",Backlog!G:G,"High",Backlog!H:H,"Candidate") -> 4
A21: LeaseTrapDetector | B21: Clauses | C21: =COUNTIFS(Backlog!B:B,"LeaseTrapDetector",Backlog!C:C,"Clauses") -> 7 | D21: =COUNTIFS(Backlog!B:B,"LeaseTrapDetector",Backlog!C:C,"Clauses",Backlog!H:H,"Shipped") -> 0 | E21: =COUNTIFS(Backlog!B:B,"LeaseTrapDetector",Backlog!C:C,"Clauses",Backlog!H:H,"Candidate") -> 7 | F21: =COUNTIFS(Backlog!B:B,"LeaseTrapDetector",Backlog!C:C,"Clauses",Backlog!G:G,"High",Backlog!H:H,"Candidate") -> 1
A22: LeaseTrapDetector | B22: Negotiation | C22: =COUNTIFS(Backlog!B:B,"LeaseTrapDetector",Backlog!C:C,"Negotiation") -> 6 | D22: =COUNTIFS(Backlog!B:B,"LeaseTrapDetector",Backlog!C:C,"Negotiation",Backlog!H:H,"Shipped") -> 0 | E22: =COUNTIFS(Backlog!B:B,"LeaseTrapDetector",Backlog!C:C,"Negotiation",Backlog!H:H,"Candidate") -> 6 | F22: =COUNTIFS(Backlog!B:B,"LeaseTrapDetector",Backlog!C:C,"Negotiation",Backlog!G:G,"High",Backlog!H:H,"Candidate") -> 1
A23: LeaseTrapDetector | B23: Landlord limits | C23: =COUNTIFS(Backlog!B:B,"LeaseTrapDetector",Backlog!C:C,"Landlord limits") -> 7 | D23: =COUNTIFS(Backlog!B:B,"LeaseTrapDetector",Backlog!C:C,"Landlord limits",Backlog!H:H,"Shipped") -> 0 | E23: =COUNTIFS(Backlog!B:B,"LeaseTrapDetector",Backlog!C:C,"Landlord limits",Backlog!H:H,"Candidate") -> 7 | F23: =COUNTIFS(Backlog!B:B,"LeaseTrapDetector",Backlog!C:C,"Landlord limits",Backlog!G:G,"High",Backlog!H:H,"Candidate") -> 3
A24: LeaseTrapDetector | B24: Post-signing | C24: =COUNTIFS(Backlog!B:B,"LeaseTrapDetector",Backlog!C:C,"Post-signing") -> 5 | D24: =COUNTIFS(Backlog!B:B,"LeaseTrapDetector",Backlog!C:C,"Post-signing",Backlog!H:H,"Shipped") -> 0 | E24: =COUNTIFS(Backlog!B:B,"LeaseTrapDetector",Backlog!C:C,"Post-signing",Backlog!H:H,"Candidate") -> 5 | F24: =COUNTIFS(Backlog!B:B,"LeaseTrapDetector",Backlog!C:C,"Post-signing",Backlog!G:G,"High",Backlog!H:H,"Candidate") -> 2
A25: LeaseTrapDetector | B25: Vetting | C25: =COUNTIFS(Backlog!B:B,"LeaseTrapDetector",Backlog!C:C,"Vetting") -> 3 | D25: =COUNTIFS(Backlog!B:B,"LeaseTrapDetector",Backlog!C:C,"Vetting",Backlog!H:H,"Shipped") -> 0 | E25: =COUNTIFS(Backlog!B:B,"LeaseTrapDetector",Backlog!C:C,"Vetting",Backlog!H:H,"Candidate") -> 3 | F25: =COUNTIFS(Backlog!B:B,"LeaseTrapDetector",Backlog!C:C,"Vetting",Backlog!G:G,"High",Backlog!H:H,"Candidate") -> 0
A26: LeaseTrapDetector | B26: Special | C26: =COUNTIFS(Backlog!B:B,"LeaseTrapDetector",Backlog!C:C,"Special") -> 3 | D26: =COUNTIFS(Backlog!B:B,"LeaseTrapDetector",Backlog!C:C,"Special",Backlog!H:H,"Shipped") -> 0 | E26: =COUNTIFS(Backlog!B:B,"LeaseTrapDetector",Backlog!C:C,"Special",Backlog!H:H,"Candidate") -> 3 | F26: =COUNTIFS(Backlog!B:B,"LeaseTrapDetector",Backlog!C:C,"Special",Backlog!G:G,"High",Backlog!H:H,"Candidate") -> 0
A27: DoctorVisitTranslator | B27: Before | C27: =COUNTIFS(Backlog!B:B,"DoctorVisitTranslator",Backlog!C:C,"Before") -> 0 | D27: =COUNTIFS(Backlog!B:B,"DoctorVisitTranslator",Backlog!C:C,"Before",Backlog!H:H,"Shipped") -> 0 | E27: =COUNTIFS(Backlog!B:B,"DoctorVisitTranslator",Backlog!C:C,"Before",Backlog!H:H,"Candidate") -> 0 | F27: =COUNTIFS(Backlog!B:B,"DoctorVisitTranslator",Backlog!C:C,"Before",Backlog!G:G,"High",Backlog!H:H,"Candidate") -> 0
A28: DoctorVisitTranslator | B28: Understand | C28: =COUNTIFS(Backlog!B:B,"DoctorVisitTranslator",Backlog!C:C,"Understand") -> 3 | D28: =COUNTIFS(Backlog!B:B,"DoctorVisitTranslator",Backlog!C:C,"Understand",Backlog!H:H,"Shipped") -> 1 | E28: =COUNTIFS(Backlog!B:B,"DoctorVisitTranslator",Backlog!C:C,"Understand",Backlog!H:H,"Candidate") -> 2 | F28: =COUNTIFS(Backlog!B:B,"DoctorVisitTranslator",Backlog!C:C,"Understand",Backlog!G:G,"High",Backlog!H:H,"Candidate") -> 0
A29: DoctorVisitTranslator | B29: Tests | C29: =COUNTIFS(Backlog!B:B,"DoctorVisitTranslator",Backlog!C:C,"Tests") -> 7 | D29: =COUNTIFS(Backlog!B:B,"DoctorVisitTranslator",Backlog!C:C,"Tests",Backlog!H:H,"Shipped") -> 0 | E29: =COUNTIFS(Backlog!B:B,"DoctorVisitTranslator",Backlog!C:C,"Tests",Backlog!H:H,"Candidate") -> 7 | F29: =COUNTIFS(Backlog!B:B,"DoctorVisitTranslator",Backlog!C:C,"Tests",Backlog!G:G,"High",Backlog!H:H,"Candidate") -> 1
A30: DoctorVisitTranslator | B30: Medication | C30: =COUNTIFS(Backlog!B:B,"DoctorVisitTranslator",Backlog!C:C,"Medication") -> 3 | D30: =COUNTIFS(Backlog!B:B,"DoctorVisitTranslator",Backlog!C:C,"Medication",Backlog!H:H,"Shipped") -> 0 | E30: =COUNTIFS(Backlog!B:B,"DoctorVisitTranslator",Backlog!C:C,"Medication",Backlog!H:H,"Candidate") -> 3 | F30: =COUNTIFS(Backlog!B:B,"DoctorVisitTranslator",Backlog!C:C,"Medication",Backlog!G:G,"High",Backlog!H:H,"Candidate") -> 0
A31: DoctorVisitTranslator | B31: Advocacy | C31: =COUNTIFS(Backlog!B:B,"DoctorVisitTranslator",Backlog!C:C,"Advocacy") -> 0 | D31: =COUNTIFS(Backlog!B:B,"DoctorVisitTranslator",Backlog!C:C,"Advocacy",Backlog!H:H,"Shipped") -> 0 | E31: =COUNTIFS(Backlog!B:B,"DoctorVisitTranslator",Backlog!C:C,"Advocacy",Backlog!H:H,"Candidate") -> 0 | F31: =COUNTIFS(Backlog!B:B,"DoctorVisitTranslator",Backlog!C:C,"Advocacy",Backlog!G:G,"High",Backlog!H:H,"Candidate") -> 0
A32: DoctorVisitTranslator | B32: Specialists | C32: =COUNTIFS(Backlog!B:B,"DoctorVisitTranslator",Backlog!C:C,"Specialists") -> 1 | D32: =COUNTIFS(Backlog!B:B,"DoctorVisitTranslator",Backlog!C:C,"Specialists",Backlog!H:H,"Shipped") -> 0 | E32: =COUNTIFS(Backlog!B:B,"DoctorVisitTranslator",Backlog!C:C,"Specialists",Backlog!H:H,"Candidate") -> 1 | F32: =COUNTIFS(Backlog!B:B,"DoctorVisitTranslator",Backlog!C:C,"Specialists",Backlog!G:G,"High",Backlog!H:H,"Candidate") -> 0
A33: DoctorVisitTranslator | B33: Diagnosis | C33: =COUNTIFS(Backlog!B:B,"DoctorVisitTranslator",Backlog!C:C,"Diagnosis") -> 3 | D33: =COUNTIFS(Backlog!B:B,"DoctorVisitTranslator",Backlog!C:C,"Diagnosis",Backlog!H:H,"Shipped") -> 0 | E33: =COUNTIFS(Backlog!B:B,"DoctorVisitTranslator",Backlog!C:C,"Diagnosis",Backlog!H:H,"Candidate") -> 3 | F33: =COUNTIFS(Backlog!B:B,"DoctorVisitTranslator",Backlog!C:C,"Diagnosis",Backlog!G:G,"High",Backlog!H:H,"Candidate") -> 1
A34: DoctorVisitPrep | B34: Before | C34: =COUNTIFS(Backlog!B:B,"DoctorVisitPrep",Backlog!C:C,"Before") -> 7 | D34: =COUNTIFS(Backlog!B:B,"DoctorVisitPrep",Backlog!C:C,"Before",Backlog!H:H,"Shipped") -> 4 | E34: =COUNTIFS(Backlog!B:B,"DoctorVisitPrep",Backlog!C:C,"Before",Backlog!H:H,"Candidate") -> 3 | F34: =COUNTIFS(Backlog!B:B,"DoctorVisitPrep",Backlog!C:C,"Before",Backlog!G:G,"High",Backlog!H:H,"Candidate") -> 0
A35: DoctorVisitPrep | B35: Understand | C35: =COUNTIFS(Backlog!B:B,"DoctorVisitPrep",Backlog!C:C,"Understand") -> 2 | D35: =COUNTIFS(Backlog!B:B,"DoctorVisitPrep",Backlog!C:C,"Understand",Backlog!H:H,"Shipped") -> 0 | E35: =COUNTIFS(Backlog!B:B,"DoctorVisitPrep",Backlog!C:C,"Understand",Backlog!H:H,"Candidate") -> 2 | F35: =COUNTIFS(Backlog!B:B,"DoctorVisitPrep",Backlog!C:C,"Understand",Backlog!G:G,"High",Backlog!H:H,"Candidate") -> 0
A36: DoctorVisitPrep | B36: Medication | C36: =COUNTIFS(Backlog!B:B,"DoctorVisitPrep",Backlog!C:C,"Medication") -> 3 | D36: =COUNTIFS(Backlog!B:B,"DoctorVisitPrep",Backlog!C:C,"Medication",Backlog!H:H,"Shipped") -> 0 | E36: =COUNTIFS(Backlog!B:B,"DoctorVisitPrep",Backlog!C:C,"Medication",Backlog!H:H,"Candidate") -> 3 | F36: =COUNTIFS(Backlog!B:B,"DoctorVisitPrep",Backlog!C:C,"Medication",Backlog!G:G,"High",Backlog!H:H,"Candidate") -> 1
A37: DoctorVisitPrep | B37: Advocacy | C37: =COUNTIFS(Backlog!B:B,"DoctorVisitPrep",Backlog!C:C,"Advocacy") -> 8 | D37: =COUNTIFS(Backlog!B:B,"DoctorVisitPrep",Backlog!C:C,"Advocacy",Backlog!H:H,"Shipped") -> 0 | E37: =COUNTIFS(Backlog!B:B,"DoctorVisitPrep",Backlog!C:C,"Advocacy",Backlog!H:H,"Candidate") -> 8 | F37: =COUNTIFS(Backlog!B:B,"DoctorVisitPrep",Backlog!C:C,"Advocacy",Backlog!G:G,"High",Backlog!H:H,"Candidate") -> 4
A38: DoctorVisitPrep | B38: Specialists | C38: =COUNTIFS(Backlog!B:B,"DoctorVisitPrep",Backlog!C:C,"Specialists") -> 2 | D38: =COUNTIFS(Backlog!B:B,"DoctorVisitPrep",Backlog!C:C,"Specialists",Backlog!H:H,"Shipped") -> 0 | E38: =COUNTIFS(Backlog!B:B,"DoctorVisitPrep",Backlog!C:C,"Specialists",Backlog!H:H,"Candidate") -> 2 | F38: =COUNTIFS(Backlog!B:B,"DoctorVisitPrep",Backlog!C:C,"Specialists",Backlog!G:G,"High",Backlog!H:H,"Candidate") -> 0
A39: DoctorVisitPrep | B39: Diagnosis | C39: =COUNTIFS(Backlog!B:B,"DoctorVisitPrep",Backlog!C:C,"Diagnosis") -> 1 | D39: =COUNTIFS(Backlog!B:B,"DoctorVisitPrep",Backlog!C:C,"Diagnosis",Backlog!H:H,"Shipped") -> 0 | E39: =COUNTIFS(Backlog!B:B,"DoctorVisitPrep",Backlog!C:C,"Diagnosis",Backlog!H:H,"Candidate") -> 1 | F39: =COUNTIFS(Backlog!B:B,"DoctorVisitPrep",Backlog!C:C,"Diagnosis",Backlog!G:G,"High",Backlog!H:H,"Candidate") -> 0
A40: TOTAL | C40: =SUM(C2:C39) -> 231 | D40: =SUM(D2:D39) -> 10 | E40: =SUM(E2:E39) -> 221 | F40: =SUM(F2:F39) -> 81

Sheet Tool Fitness
A1: Tool | B1: Tagline | C1: SEO Fit | D1: Est. Queries | E1: Status | F1: Notes | H1: Totals | I1: Tools | J1: Est. Queries
A2: DifficultTalkCoach | B2: Practice hard conversations before they happen | C2: HIGH | D2: 96 | E2: Done | F2: Shipped: 5 guides | H2: HIGH | I2: =COUNTIF(C:C,"HIGH") -> 16 | J2: =SUMIF(C:C,"HIGH",D:D) -> 464
A3: UpsellShield | B3: Walk into high-pressure sales prepared | C3: HIGH | D3: 57 | E3: Done | F3: Discovered; subscription cluster may reassign to SubscriptionGuiltTrip | H3: MEDIUM | I3: =COUNTIF(C:C,"MEDIUM") -> 35 | J3: =SUMIF(C:C,"MEDIUM",D:D) -> 336
A4: DoctorVisitTranslator | B4: Turn medical jargon into plain English | C4: HIGH | D4: 17 | E4: Done | F4: Owns translation/comprehension of results — what the doctor said, medical jargon, test and imaging reports, medication side effects, diagnoses. All asking and prep-for-discussion goes to DoctorVisitPrep. | H4: LOW | I4: =COUNTIF(C:C,"LOW") -> 40 | J4: =SUMIF(C:C,"LOW",D:D) -> 131
A5: DoctorVisitPrep | B5: TBD — confirm with deployed copy | C5: HIGH | D5: 23 | E5: Done | F5: Owns preparation for the discussion — visit prep, advocacy strategy, how-to-ask, how-to-talk-to. Split off from DVT this session. | H5: NONE | I5: =COUNTIF(C:C,"NONE") -> 28 | J5: =SUMIF(C:C,"NONE",D:D) -> 0
A6: LeaseTrapDetector | B6: Find predatory clauses hiding in your lease | C6: HIGH | D6: 38 | E6: Done | F6: Discovered | H6: TOTAL | I6: =SUM(I2:I5) -> 119 | J6: =SUM(J2:J5) -> 931
A7: PetWeirdnessDecoder | B7: Is it quirky or concerning? | C7: HIGH | D7: 30 | E7: Queue | F7: Huge cluster: 'why is my cat/dog X' queries
A8: PlantRescue | B8: Why are my leaves turning yellow? | C8: HIGH | D8: 30 | E8: Queue | F8: Huge cluster: 'why is my plant X' queries
A9: BikeMedic | B9: A trailside mechanic in your pocket | C9: HIGH | D9: 25 | E9: Queue | F9: 'How to fix a bike X' cluster — technical repair
A10: ConflictCoach | B10: Stop, breathe, and craft the right response | C10: HIGH | D10: 25 | E10: Triage | F10: Heavy DTC overlap — triage which tool owns which queries
A11: ComplaintEscalationWriter | B11: Full escalation campaigns companies can't ignore | C11: HIGH | D11: 20 | E11: Queue | F11: 'How to file/escalate complaint against X' cluster
A12: MarkupDetective | B12: Why does this cost that? Follow the money | C12: HIGH | D12: 20 | E12: Queue | F12: Overdue: UpsellShield flagged 4 overlap queries
A13: RulebookBreaker | B13: Loopholes, magic words, escalation ladder | C13: HIGH | D13: 20 | E13: Queue | F13: Overlaps UpsellShield/ComplaintEscalationWriter
A14: BillRescue | B14: Your bill anxiety ends here | C14: HIGH | D14: 18 | E14: Queue | F14: 'How to dispute/negotiate/read a bill' — overlaps MarkupDetective
A15: RentersDepositSaver | B15: Protect your security deposit on move-in day | C15: HIGH | D15: 15 | E15: Queue | F15: Distinct from LeaseTrapDetector (move-in moment)
A16: SubscriptionGuiltTrip | B16: Cancel what you don't use. Negotiate what you keep | C16: HIGH | D16: 15 | E16: Triage | F16: REASSIGN: UpsellShield Subscriptions cluster likely belongs here
A17: ToastWriter | B17: Toasts, speeches, and tributes that land | C17: HIGH | D17: 15 | E17: Queue | F17: Wedding/funeral toast queries are high-volume, high-intent
A18: Giftology | B18: The perfect gift for the hardest person to shop for | C18: MEDIUM | D18: 15 | E18: Queue | F18: 'Gift ideas for X' — huge volume but very competitive
... A120: WrongAnswersOnly | B120: Get a confidently, beautifully wrong answer | C120: NONE | D120: 0 | E120: Skip | F120: Humor

Sheet Legend
A1: DeftBrain Guide Backlog — Legend
A3: Columns
A4: ID | B4: Sequential within the tool. For reference; not a URL.
A5: Tool | B5: Which DeftBrain tool the guide CTAs to.
A6: Cluster | B6: Query-space cluster within this tool. Used for writing rhythm.
A7: Query (Guide Title) | B7: The actual phrase someone would Google. The guide ranks for this.
A8: Slug | B8: URL slug. Lowercase, hyphenated, apostrophes removed. Auto-derived from query.
A9: Category | B9: Top-level section on deftbrain.com/guides. Current: workplace, conversations.
A10: Priority | B10: High / Medium / Low — by likely volume × intent × competitive fit.
A11: Status | B11: Candidate (not yet written) / Drafting / Shipped.
A12: Notes | B12: Context, overlaps with other tools, voice flags, etc.
A14: Priority color coding
A15: High | B15: Soft amber — the queries to write first.
A16: Medium | B16: Soft yellow — second-wave candidates.
A17: Low | B17: Soft green — write only when cluster is nearly saturated.
A19: Voice flags
A20: Hard news cluster | B20: Standard voice rules do NOT apply. No dry humor. Full empathy register. When writing these, consider a modified voice spec.
A21: Overlap notes | B21: Some queries plausibly serve multiple tools. Triage is deferred until every tool has its own discovery pass. Marked 'OVERLAP' in Notes.
A23: Workflow
A24: 1 | B24: A tool's discovery pass adds its queries to the Backlog sheet.
A25: 2 | B25: Priorities and category assignments get reviewed.
A26: 3 | B26: Candidates are drafted (style guide + existing specs as reference).
A27: 4 | B27: Status moves to Shipped when the guide is live.
A28: 5 | B28: Summary sheet auto-updates from the Backlog via COUNTIFS formulas.
A30: Categories used
A31: workplace | B31: Work/manager/coworker/team communication (existing).
A32: conversations | B32: Personal conversations — partner, family, friends, hard news (new, introduced with DifficultTalkCoach pass).
A33: consumer | B33: Buying, selling, negotiating, subscriptions, consumer defense (new, introduced with UpsellShield pass).
A34: home | B34: Housing, rentals, leases, home ownership, household admin (introduced with LeaseTrapDetector pass).
A35: health | B35: Patient-doctor communication, medical literacy, test results, medication, serious diagnoses (introduced with DoctorVisitTranslator pass; expanded with DoctorVisitPrep for visit-prep and advocacy strategy).
